LICENSE.txt
MANIFEST.in
README.rst
REL_NOTES.rst
setup.cfg
setup.py
query_collections/__init__.py
query_collections/exceptions.py
query_collections/filters.py
query_collections/query_structs.py
query_collections/search.py
query_collections.egg-info/PKG-INFO
query_collections.egg-info/SOURCES.txt
query_collections.egg-info/dependency_links.txt
query_collections.egg-info/requires.txt
query_collections.egg-info/top_level.txt