Metadata-Version: 1.1
Name: query-collections
Version: 0.0.1.2a10
Summary: A set of classes built for easier management of Python maps and lists
Home-page: https://github.com/c4wrd/query_collections
Author: Cory Forward
Author-email: coryf96@gmail.com
License: MIT
Keywords: json dictionary management query selection
Platform: UNKNOWN
Classifier: Development Status :: 3 - Alpha
Classifier: Intended Audience :: Developers
Classifier: Topic :: Software Development :: Build Tools
Classifier: License :: OSI Approved :: MIT License
Classifier: Programming Language :: Python :: 2.7
Classifier: Programming Language :: Python :: 3.2
Classifier: Programming Language :: Python :: 3.3
Classifier: Programming Language :: Python :: 3.4
Classifier: Programming Language :: Python :: 3.5
